optscale_arcee/__init__.py
optscale_arcee/arcee.py
optscale_arcee/name_generator.py
optscale_arcee/platform.py
optscale_arcee/hw_stat_collector/__init__.py
optscale_arcee/hw_stat_collector/collector.py
optscale_arcee/module_collector/__init__.py
optscale_arcee/module_collector/collector.py
optscale_arcee/platforms_meta/__init__.py
optscale_arcee/platforms_meta/azure.py
optscale_arcee/sender/__init__.py
optscale_arcee/sender/sender.py
sender/__init__.py
sender/name_generator.py
sender/platform.py
sender/sender.py
sender/hw_stat_collector/__init__.py
sender/hw_stat_collector/collector.py
sender/module_collector/__init__.py
sender/module_collector/collector.py
sender/platforms_meta/__init__.py
sender/platforms_meta/azure.py
tests/__init__.py
tests/test_data.py
tests/test_platform.py
optscale_arcee-0.1.18.dist-info/LICENSE.txt
optscale_arcee-0.1.18.dist-info/METADATA
optscale_arcee-0.1.18.dist-info/WHEEL
optscale_arcee-0.1.18.dist-info/top_level.txt
optscale_arcee-0.1.18.dist-info/RECORD
