Metadata-Version: 2.1
Name: optscale-arcee
Version: 0.1.18
Summary: ML profiling tool for OptScale
Home-page: https://my.optscale.com/
Author: Hystax
License: UNKNOWN
Keywords: arcee,ml,optscale,finops
Platform: UNKNOWN
Requires-Python: <4,>=3.7
License-File: LICENSE.txt
Requires-Dist: aiohttp (==3.8.1)
Requires-Dist: aiofiles (==22.1.0)
Requires-Dist: GPUtil (==1.4.0)
Requires-Dist: psutil (==5.9.2)
